datafed/CLI.py
datafed/CommandLib.py
datafed/Config.py
datafed/Connection.py
datafed/MessageLib.py
datafed/SDMS_Anon_pb2.py
datafed/SDMS_Auth_pb2.py
datafed/SDMS_pb2.py
datafed/VERSION.py
datafed/VersionUtils.py
datafed/Version_pb2.py
datafed/__init__.py
datafed-3.0.3.dist-info/METADATA
datafed-3.0.3.dist-info/WHEEL
datafed-3.0.3.dist-info/entry_points.txt
datafed-3.0.3.dist-info/top_level.txt
datafed-3.0.3.dist-info/RECORD
