Metadata-Version: 2.1
Name: datafed
Version: 3.0.3
Summary: DataFed CLI and API
Home-page: https://github.com/ORNL/DataFed
Author: Dale Stansberry, Joshua Brown
Author-email: stansberrydv@ornl.gov, brownjs@ornl.gov
Classifier: Programming Language :: Python :: 3
Classifier: License :: OSI Approved :: MIT License
Classifier: Operating System :: OS Independent
Requires-Dist: click >=7
Requires-Dist: prompt-toolkit >=2
Requires-Dist: protobuf >=5.27.1
Requires-Dist: pyzmq >=16
Requires-Dist: requests >=2
Requires-Dist: wget >=3
